spotify_bulk_actions_mcp/__init__.py
spotify_bulk_actions_mcp/server.py
spotify_bulk_actions_mcp/spotify_client.py
spotify_bulk_actions_mcp/tools/__init__.py
spotify_bulk_actions_mcp/tools/library.py
spotify_bulk_actions_mcp/tools/playlist.py
spotify_bulk_actions_mcp/tools/search.py
spotify_bulk_actions_mcp/utils/__init__.py
spotify_bulk_actions_mcp/utils/auth.py
spotify_bulk_actions_mcp/utils/cache.py
spotify_bulk_actions_mcp-0.1.1.dist-info/METADATA
spotify_bulk_actions_mcp-0.1.1.dist-info/WHEEL
spotify_bulk_actions_mcp-0.1.1.dist-info/entry_points.txt
spotify_bulk_actions_mcp-0.1.1.dist-info/licenses/LICENSE
spotify_bulk_actions_mcp-0.1.1.dist-info/RECORD
