Metadata-Version: 2.4
Name: spotify-bulk-actions-mcp
Version: 0.1.1
Summary: MCP server for bulk Spotify operations with confidence-scored song matching, batch playlist creation, and library exports
Project-URL: Homepage, https://github.com/khglynn/spotify-bulk-actions-mcp
Project-URL: Repository, https://github.com/khglynn/spotify-bulk-actions-mcp
Project-URL: Issues, https://github.com/khglynn/spotify-bulk-actions-mcp/issues
Author-email: Kevin Glynn <kevin@khglynn.com>
License-Expression: MIT
License-File: LICENSE
Keywords: bulk-operations,claude,mcp,model-context-protocol,music,playlist,spotify
Classifier: Development Status :: 4 - Beta
Classifier: Intended Audience :: Developers
Classifier: License :: OSI Approved :: MIT License
Classifier: Programming Language :: Python :: 3
Classifier: Programming Language :: Python :: 3.10
Classifier: Programming Language :: Python :: 3.11
Classifier: Programming Language :: Python :: 3.12
Classifier: Topic :: Multimedia :: Sound/Audio
Requires-Python: >=3.10
Requires-Dist: fastmcp>=0.1.0
Requires-Dist: httpx>=0.25.0
Requires-Dist: python-dotenv>=1.0.0
Requires-Dist: python-levenshtein>=0.23.0
Requires-Dist: spotipy>=2.23.0
Requires-Dist: thefuzz>=0.22.0
